ddeutil/core/__about__.py
ddeutil/core/__init__.py
ddeutil/core/decorator.py
ddeutil/core/dtutils.py
ddeutil/core/threader.py
ddeutil/core/base/__init__.py
ddeutil/core/base/checker.py
ddeutil/core/base/convert.py
ddeutil/core/base/hash.py
ddeutil/core/base/merge.py
ddeutil/core/base/sorting.py
ddeutil/core/base/splitter.py
ddeutil-0.4.10.dist-info/licenses/LICENSE
ddeutil-0.4.10.dist-info/METADATA
ddeutil-0.4.10.dist-info/WHEEL
ddeutil-0.4.10.dist-info/top_level.txt
ddeutil-0.4.10.dist-info/RECORD
