Metadata-Version: 2.4
Name: ddeutil
Version: 0.4.10
Summary: Core Utility functions and objects
Author-email: korawica <korawich.anu@gmail.com>
License: MIT
Project-URL: Homepage, https://github.com/ddeutils/ddeutil/
Project-URL: Source Code, https://github.com/ddeutils/ddeutil/
Keywords: data,utility
Classifier: Topic :: Utilities
Classifier: Natural Language :: English
Classifier: Development Status :: 4 - Beta
Classifier: Intended Audience :: Developers
Classifier: Operating System :: OS Independent
Classifier: Programming Language :: Python
Classifier: Programming Language :: Python :: 3 :: Only
Classifier: Programming Language :: Python :: 3.9
Classifier: Programming Language :: Python :: 3.10
Classifier: Programming Language :: Python :: 3.11
Classifier: Programming Language :: Python :: 3.12
Classifier: Programming Language :: Python :: 3.13
Requires-Python: >=3.9.13
License-File: LICENSE
Provides-Extra: all
Requires-Dist: ujson==5.10.0; extra == "all"
Requires-Dist: python-dateutil==2.9.0.post0; extra == "all"
Requires-Dist: types-python-dateutil==2.9.0.20250516; extra == "all"
Requires-Dist: psutil==7.0.0; extra == "all"
Provides-Extra: checksum
Requires-Dist: ujson==5.10.0; extra == "checksum"
Provides-Extra: dateutil
Requires-Dist: python-dateutil==2.9.0.post0; extra == "dateutil"
Requires-Dist: types-python-dateutil==2.9.0.20250516; extra == "dateutil"
Provides-Extra: memory
Requires-Dist: psutil==7.0.0; extra == "memory"
Dynamic: license-file
